tocky/__init__.py
tocky/bulk_processor.py
tocky/detector/__init__.py
tocky/detector/ai_vision_detector.py
tocky/detector/manual_detector.py
tocky/detector/ocr_detector.py
tocky/detector/tests.py
tocky/env.py
tocky/extractor/__init__.py
tocky/extractor/ai_extractor.py
tocky/extractor/ai_vision_extractor.py
tocky/extractor/formats.py
tocky/ocr/__init__.py
tocky/ocr/azure.py
tocky/ocr/easyocr.py
tocky/ocr/printer.py
tocky/ocr/tesseract/__init__.py
tocky/ocr/tesseract/preprocessing.py
tocky/prompt_samples.yaml
tocky/utils/__init__.py
tocky/utils/ia.py
tocky/utils/llm.py
tocky/validator.py
tocky-0.0.17.dist-info/LICENSE
tocky-0.0.17.dist-info/METADATA
tocky-0.0.17.dist-info/WHEEL
tocky-0.0.17.dist-info/RECORD
